README.txt
setup.py
cs/__init__.py
cs.pfg.dnivalidator.egg-info/PKG-INFO
cs.pfg.dnivalidator.egg-info/SOURCES.txt
cs.pfg.dnivalidator.egg-info/dependency_links.txt
cs.pfg.dnivalidator.egg-info/entry_points.txt
cs.pfg.dnivalidator.egg-info/namespace_packages.txt
cs.pfg.dnivalidator.egg-info/not-zip-safe
cs.pfg.dnivalidator.egg-info/paster_plugins.txt
cs.pfg.dnivalidator.egg-info/requires.txt
cs.pfg.dnivalidator.egg-info/top_level.txt
cs/pfg/__init__.py
cs/pfg/dnivalidator/__init__.py
cs/pfg/dnivalidator/configure.zcml
cs/pfg/dnivalidator/dni.py
cs/pfg/dnivalidator/patches.py
cs/pfg/dnivalidator/version.txt
docs/HISTORY.txt
docs/INSTALL.txt
docs/LICENSE.GPL
docs/LICENSE.txt