Metadata-Version: 1.1
Name: cs.pfg.dnivalidator
Version: 0.3
Summary: A package that adds a Spanish ID card number validator for PloneFormGen
Home-page: http://code.codesyntax.com/private/cs.pfg.dnivalidator
Author: Mikel Larreategi
Author-email: mlarreategi@codesyntax.com
License: GPL
Platform: UNKNOWN
Classifier: Framework :: Plone
Classifier: Programming Language :: Python
Classifier: Topic :: Software Development :: Libraries :: Python Modules
